Flask_Settings-0.0.3.dist-info/DESCRIPTION.rst
Flask_Settings-0.0.3.dist-info/METADATA
Flask_Settings-0.0.3.dist-info/RECORD
Flask_Settings-0.0.3.dist-info/WHEEL
Flask_Settings-0.0.3.dist-info/metadata.json
Flask_Settings-0.0.3.dist-info/top_level.txt
flask_settings/__init__.py
flask_settings/basic.py
flask_settings/factory.py
flask_settings/globals.py
