Metadata-Version: 2.0
Name: Flask-Settings
Version: 0.0.3
Summary: Flask settings extension is similar to Django settings.
Home-page: https://github.com/left-join/flask-settings
Author: left-join
Author-email: left-join@riseup.net
License: MIT
Download-URL: https://github.com/left-join/flask-settings.git
Keywords: flask,settings
Platform: any
Classifier: Environment :: Web Environment
Classifier: Intended Audience :: Developers
Classifier: License :: OSI Approved :: MIT License
Classifier: Operating System :: OS Independent
Classifier: Topic :: Internet :: WWW/HTTP :: Dynamic Content
Classifier: Topic :: Software Development :: Libraries :: Python Modules
Classifier: Programming Language :: Python
Classifier: Programming Language :: Python :: 2.6
Classifier: Programming Language :: Python :: 2.7
Classifier: Programming Language :: Python :: 3.4
Classifier: Programming Language :: Python :: 3.5
Classifier: Programming Language :: Python :: 3.6
Classifier: Programming Language :: Python :: 3.5
Requires-Dist: flask (>=0.12.2)
